teams_report_converter/__init__.py
teams_report_converter/__main__.py
teams_report_converter/report_handler.py
teams_report_converter-0.2.0.dist-info/LICENSE
teams_report_converter-0.2.0.dist-info/METADATA
teams_report_converter-0.2.0.dist-info/WHEEL
teams_report_converter-0.2.0.dist-info/entry_points.txt
teams_report_converter-0.2.0.dist-info/top_level.txt
teams_report_converter-0.2.0.dist-info/RECORD
