Metadata-Version: 2.1
Name: teams-report-converter
Version: 0.2.0
Summary: Convert meaningless MS Teams attendance text reports into calculated attendance spreadsheets
Author-email: Renê Fernandes <renefb@proton.me>
License: MIT License
Project-URL: Homepage, https://github.com/renefb/teams-report-converter
Keywords: microsoft,teams,events,broadcast,attendance,report,conversion,spreadsheet
Classifier: Development Status :: 4 - Beta
Classifier: Intended Audience :: Developers
Classifier: Intended Audience :: End Users/Desktop
Classifier: License :: OSI Approved :: MIT License
Classifier: Operating System :: OS Independent
Classifier: Programming Language :: Python
Classifier: Programming Language :: Python :: 3
Classifier: Topic :: Office/Business
Classifier: Topic :: Terminals
Classifier: Topic :: Utilities
Requires-Python: >=3.6
License-File: LICENSE
Requires-Dist: pandas
Requires-Dist: openpyxl
